AUTHORS.rst
CONTRIBUTING.rst
HISTORY.rst
LICENSE
MANIFEST.in
README.rst
setup.cfg
setup.py
pipe/__init__.py
pipe/pipe.py
test/test_pipe.py
warp_pipe.egg-info/PKG-INFO
warp_pipe.egg-info/SOURCES.txt
warp_pipe.egg-info/dependency_links.txt
warp_pipe.egg-info/not-zip-safe
warp_pipe.egg-info/top_level.txt