Metadata-Version: 1.1
Name: warp-pipe
Version: 0.1.0
Summary: Testbed for Tensorflow 2.0 TFX
Home-page: https://github.com/yngtodd/pipe
Author: Todd Young
Author-email: ygx@ornl.gov
License: MIT
Keywords: pipe
Platform: UNKNOWN
Classifier: Development Status :: 2 - Pre-Alpha
Classifier: Intended Audience :: Developers
Classifier: License :: OSI Approved :: MIT License
Classifier: Natural Language :: English
Classifier: Programming Language :: Python :: 3.6
Classifier: Programming Language :: Python :: Implementation :: PyPy
